linearfit/__init__.py
linearfit/linearfit.py
linearfit-1.0.2.data/scripts/test_linearfit.py
linearfit-1.0.2.dist-info/AUTHORS.rst
linearfit-1.0.2.dist-info/LICENSE
linearfit-1.0.2.dist-info/METADATA
linearfit-1.0.2.dist-info/WHEEL
linearfit-1.0.2.dist-info/top_level.txt
linearfit-1.0.2.dist-info/RECORD
